<annotation>
	<folder>img</folder>
	<filename>a73.jpg</filename>
	<path>C:\Users\mom\Desktop\img\a73.jpg</path>
	<source>
		<database>Unknown</database>
	</source>
	<size>
		<width>0</width>
		<height>0</height>
		<depth>3</depth>
	</size>
	<segmented>0</segmented>
	<object>
		<name>Red</name>
		<pose>Unspecified</pose>
		<truncated>0</truncated>
		<difficult>0</difficult>
		<bndbox>
			<xmin>218</xmin>
			<ymin>122</ymin>
			<xmax>234</xmax>
			<ymax>148</ymax>
		</bndbox>
	</object>
</annotation>
