<annotation>
	<folder>img</folder>
	<filename>a160.jpg</filename>
	<path>C:\Users\mom\Desktop\img\a160.jpg</path>
	<source>
		<database>Unknown</database>
	</source>
	<size>
		<width>0</width>
		<height>0</height>
		<depth>3</depth>
	</size>
	<segmented>0</segmented>
	<object>
		<name>Speed50</name>
		<pose>Unspecified</pose>
		<truncated>0</truncated>
		<difficult>0</difficult>
		<bndbox>
			<xmin>266</xmin>
			<ymin>258</ymin>
			<xmax>294</xmax>
			<ymax>284</ymax>
		</bndbox>
	</object>
	<object>
		<name>Speed30</name>
		<pose>Unspecified</pose>
		<truncated>0</truncated>
		<difficult>0</difficult>
		<bndbox>
			<xmin>281</xmin>
			<ymin>288</ymin>
			<xmax>316</xmax>
			<ymax>322</ymax>
		</bndbox>
	</object>
	<object>
		<name>Stop</name>
		<pose>Unspecified</pose>
		<truncated>0</truncated>
		<difficult>0</difficult>
		<bndbox>
			<xmin>353</xmin>
			<ymin>281</ymin>
			<xmax>388</xmax>
			<ymax>314</ymax>
		</bndbox>
	</object>
</annotation>
